testcases_executor/__init__.py
testcases_executor/__main__.py
testcases_executor/tc_groups.py
testcases_executor/tc_parser.py
testcases_executor/tc_result.py
testcases_executor/tc_runner.py
testcases_executor/tc_utils.py
testcases_executor/tc_reporter/__init__.py
testcases_executor/tc_reporter/contexts.py
testcases_executor/tc_reporter/html_report.py
testcases_executor/tc_reporter/templates/groups.html
testcases_executor/tc_reporter/templates/header.html
testcases_executor/tc_reporter/templates/info_list.html
testcases_executor/tc_reporter/templates/report_template.html
testcases_executor/tc_reporter/templates/test_line.html
testcases_executor/tc_reporter/templates/testcase.html
testcases_executor/tests/__init__.py
testcases_executor/tests/test_main.py
testcases_executor/tests/test_tc_groups.py
testcases_executor/tests/test_tc_parser.py
testcases_executor/tests/test_tc_result.py
testcases_executor/tests/test_tc_runner.py
testcases_executor/tests/test_tc_utils.py
testcases_executor/tests/test_tc_reporter/__init__.py
testcases_executor/tests/test_tc_reporter/test_contexts.py
testcases_executor/tests/test_tc_reporter/test_html_report.py
testcases_executor-1.0.0.dist-info/LICENSE
testcases_executor-1.0.0.dist-info/METADATA
testcases_executor-1.0.0.dist-info/WHEEL
testcases_executor-1.0.0.dist-info/top_level.txt
testcases_executor-1.0.0.dist-info/RECORD
