Metadata-Version: 2.1
Name: testcases-executor
Version: 1.0.0
Summary: Executor of unittest.TestCase subclasses ordered by groups.
Home-page: https://github.com/JBthePenguin/TestCasesExecutor
Author: JBthePenguin
Author-email: jbthepenguin@netcourrier.com
License: UNKNOWN
Platform: UNKNOWN
Classifier: Programming Language :: Python :: 3
Classifier: License :: OSI Approved :: GNU General Public License v3 (GPLv3)
Classifier: Operating System :: OS Independent
Requires-Python: >=3.8
Requires-Dist: jinja2
